Metadata-Version: 1.1
Name: butterfly-latest
Version: 3.0.2
Summary: A sleek web based terminal emulator
Home-page: http://github.com/paradoxxxzero/butterfly
Author: Florian Mounier
Author-email: paradoxxx.zero@gmail.com
License: GPLv3
Platform: Any
Classifier: Development Status :: 4 - Beta
Classifier: Intended Audience :: Developers
Classifier: License :: OSI Approved :: GNU General Public License v3 (GPLv3)
Classifier: Operating System :: POSIX :: Linux
Classifier: Programming Language :: Python :: 2
Classifier: Programming Language :: Python :: 3
Classifier: Topic :: Terminals
